{
  "locked": false,
  "version": 2,
  "targets": {
    ".NETFramework,Version=v4.0": {
      "Hammock/1.3.1": {
        "type": "package",
        "compile": {
          "lib/4.0/Hammock.ClientProfile.dll": {},
          "lib/4.0/Hammock.dll": {}
        },
        "runtime": {
          "lib/4.0/Hammock.ClientProfile.dll": {},
          "lib/4.0/Hammock.dll": {}
        }
      },
      "IrcDotNet/0.5.0": {
        "type": "project",
        "framework": ".NETFramework,Version=v4.0"
      },
      "IrcDotNet.Samples.Common/0.5.0": {
        "type": "project",
        "framework": ".NETFramework,Version=v4.0",
        "dependencies": {
          "IrcDotNet": null
        }
      },
      "Newtonsoft.Json/5.0.6": {
        "type": "package",
        "compile": {
          "lib/net40/Newtonsoft.Json.dll": {}
        },
        "runtime": {
          "lib/net40/Newtonsoft.Json.dll": {}
        }
      },
      "TweetSharp/2.3.1": {
        "type": "package",
        "dependencies": {
          "Newtonsoft.Json": "5.0.6"
        },
        "compile": {
          "lib/4.0/Hammock.ClientProfile.dll": {},
          "lib/4.0/Newtonsoft.Json.dll": {},
          "lib/4.0/TweetSharp.dll": {}
        },
        "runtime": {
          "lib/4.0/Hammock.ClientProfile.dll": {},
          "lib/4.0/Newtonsoft.Json.dll": {},
          "lib/4.0/TweetSharp.dll": {}
        }
      }
    },
    ".NETFramework,Version=v4.5": {
      "Hammock/1.3.1": {
        "type": "package",
        "compile": {
          "lib/4.0/Hammock.ClientProfile.dll": {},
          "lib/4.0/Hammock.dll": {}
        },
        "runtime": {
          "lib/4.0/Hammock.ClientProfile.dll": {},
          "lib/4.0/Hammock.dll": {}
        }
      },
      "IrcDotNet/0.5.0": {
        "type": "project",
        "framework": ".NETFramework,Version=v4.5"
      },
      "IrcDotNet.Samples.Common/0.5.0": {
        "type": "project",
        "framework": ".NETFramework,Version=v4.5",
        "dependencies": {
          "IrcDotNet": null
        }
      },
      "Newtonsoft.Json/5.0.6": {
        "type": "package",
        "compile": {
          "lib/net45/Newtonsoft.Json.dll": {}
        },
        "runtime": {
          "lib/net45/Newtonsoft.Json.dll": {}
        }
      },
      "TweetSharp/2.3.1": {
        "type": "package",
        "dependencies": {
          "Newtonsoft.Json": "5.0.6"
        },
        "compile": {
          "lib/4.0/Hammock.ClientProfile.dll": {},
          "lib/4.0/Newtonsoft.Json.dll": {},
          "lib/4.0/TweetSharp.dll": {}
        },
        "runtime": {
          "lib/4.0/Hammock.ClientProfile.dll": {},
          "lib/4.0/Newtonsoft.Json.dll": {},
          "lib/4.0/TweetSharp.dll": {}
        }
      }
    },
    ".NETFramework,Version=v4.5.1": {
      "Hammock/1.3.1": {
        "type": "package",
        "compile": {
          "lib/4.0/Hammock.ClientProfile.dll": {},
          "lib/4.0/Hammock.dll": {}
        },
        "runtime": {
          "lib/4.0/Hammock.ClientProfile.dll": {},
          "lib/4.0/Hammock.dll": {}
        }
      },
      "IrcDotNet/0.5.0": {
        "type": "project",
        "framework": ".NETFramework,Version=v4.5.1"
      },
      "IrcDotNet.Samples.Common/0.5.0": {
        "type": "project",
        "framework": ".NETFramework,Version=v4.5.1",
        "dependencies": {
          "IrcDotNet": null
        }
      },
      "Newtonsoft.Json/5.0.6": {
        "type": "package",
        "compile": {
          "lib/net45/Newtonsoft.Json.dll": {}
        },
        "runtime": {
          "lib/net45/Newtonsoft.Json.dll": {}
        }
      },
      "TweetSharp/2.3.1": {
        "type": "package",
        "dependencies": {
          "Newtonsoft.Json": "5.0.6"
        },
        "compile": {
          "lib/4.0/Hammock.ClientProfile.dll": {},
          "lib/4.0/Newtonsoft.Json.dll": {},
          "lib/4.0/TweetSharp.dll": {}
        },
        "runtime": {
          "lib/4.0/Hammock.ClientProfile.dll": {},
          "lib/4.0/Newtonsoft.Json.dll": {},
          "lib/4.0/TweetSharp.dll": {}
        }
      }
    },
    "DNX,Version=v4.5.1": {
      "Hammock/1.3.1": {
        "type": "package",
        "compile": {
          "lib/4.0/Hammock.ClientProfile.dll": {},
          "lib/4.0/Hammock.dll": {}
        },
        "runtime": {
          "lib/4.0/Hammock.ClientProfile.dll": {},
          "lib/4.0/Hammock.dll": {}
        }
      },
      "IrcDotNet/0.5.0": {
        "type": "project",
        "framework": "DNX,Version=v4.5.1"
      },
      "IrcDotNet.Samples.Common/0.5.0": {
        "type": "project",
        "framework": "DNX,Version=v4.5.1",
        "dependencies": {
          "IrcDotNet": null
        }
      },
      "Newtonsoft.Json/5.0.6": {
        "type": "package",
        "compile": {
          "lib/net45/Newtonsoft.Json.dll": {}
        },
        "runtime": {
          "lib/net45/Newtonsoft.Json.dll": {}
        }
      },
      "TweetSharp/2.3.1": {
        "type": "package",
        "dependencies": {
          "Newtonsoft.Json": "5.0.6"
        },
        "compile": {
          "lib/4.0/Hammock.ClientProfile.dll": {},
          "lib/4.0/Newtonsoft.Json.dll": {},
          "lib/4.0/TweetSharp.dll": {}
        },
        "runtime": {
          "lib/4.0/Hammock.ClientProfile.dll": {},
          "lib/4.0/Newtonsoft.Json.dll": {},
          "lib/4.0/TweetSharp.dll": {}
        }
      }
    },
    "DNX,Version=v5.0": {
      "Hammock/1.3.1": {
        "type": "package",
        "compile": {
          "lib/4.0/Hammock.ClientProfile.dll": {},
          "lib/4.0/Hammock.dll": {}
        },
        "runtime": {
          "lib/4.0/Hammock.ClientProfile.dll": {},
          "lib/4.0/Hammock.dll": {}
        }
      },
      "IrcDotNet/0.5.0": {
        "type": "project",
        "framework": "DNX,Version=v4.5.1"
      },
      "IrcDotNet.Samples.Common/0.5.0": {
        "type": "project",
        "framework": "DNX,Version=v5.0",
        "dependencies": {
          "IrcDotNet": null
        }
      },
      "Newtonsoft.Json/5.0.6": {
        "type": "package",
        "compile": {
          "lib/net45/Newtonsoft.Json.dll": {}
        },
        "runtime": {
          "lib/net45/Newtonsoft.Json.dll": {}
        }
      },
      "TweetSharp/2.3.1": {
        "type": "package",
        "dependencies": {
          "Newtonsoft.Json": "5.0.6"
        },
        "compile": {
          "lib/4.0/Hammock.ClientProfile.dll": {},
          "lib/4.0/Newtonsoft.Json.dll": {},
          "lib/4.0/TweetSharp.dll": {}
        },
        "runtime": {
          "lib/4.0/Hammock.ClientProfile.dll": {},
          "lib/4.0/Newtonsoft.Json.dll": {},
          "lib/4.0/TweetSharp.dll": {}
        }
      }
    },
    ".NETFramework,Version=v4.0/win7-x86": {
      "Hammock/1.3.1": {
        "type": "package",
        "compile": {
          "lib/4.0/Hammock.ClientProfile.dll": {},
          "lib/4.0/Hammock.dll": {}
        },
        "runtime": {
          "lib/4.0/Hammock.ClientProfile.dll": {},
          "lib/4.0/Hammock.dll": {}
        }
      },
      "IrcDotNet/0.5.0": {
        "type": "project",
        "framework": ".NETFramework,Version=v4.0"
      },
      "IrcDotNet.Samples.Common/0.5.0": {
        "type": "project",
        "framework": ".NETFramework,Version=v4.0",
        "dependencies": {
          "IrcDotNet": null
        }
      },
      "Newtonsoft.Json/5.0.6": {
        "type": "package",
        "compile": {
          "lib/net40/Newtonsoft.Json.dll": {}
        },
        "runtime": {
          "lib/net40/Newtonsoft.Json.dll": {}
        }
      },
      "TweetSharp/2.3.1": {
        "type": "package",
        "dependencies": {
          "Newtonsoft.Json": "5.0.6"
        },
        "compile": {
          "lib/4.0/Hammock.ClientProfile.dll": {},
          "lib/4.0/Newtonsoft.Json.dll": {},
          "lib/4.0/TweetSharp.dll": {}
        },
        "runtime": {
          "lib/4.0/Hammock.ClientProfile.dll": {},
          "lib/4.0/Newtonsoft.Json.dll": {},
          "lib/4.0/TweetSharp.dll": {}
        }
      }
    },
    ".NETFramework,Version=v4.0/win7-x64": {
      "Hammock/1.3.1": {
        "type": "package",
        "compile": {
          "lib/4.0/Hammock.ClientProfile.dll": {},
          "lib/4.0/Hammock.dll": {}
        },
        "runtime": {
          "lib/4.0/Hammock.ClientProfile.dll": {},
          "lib/4.0/Hammock.dll": {}
        }
      },
      "IrcDotNet/0.5.0": {
        "type": "project",
        "framework": ".NETFramework,Version=v4.0"
      },
      "IrcDotNet.Samples.Common/0.5.0": {
        "type": "project",
        "framework": ".NETFramework,Version=v4.0",
        "dependencies": {
          "IrcDotNet": null
        }
      },
      "Newtonsoft.Json/5.0.6": {
        "type": "package",
        "compile": {
          "lib/net40/Newtonsoft.Json.dll": {}
        },
        "runtime": {
          "lib/net40/Newtonsoft.Json.dll": {}
        }
      },
      "TweetSharp/2.3.1": {
        "type": "package",
        "dependencies": {
          "Newtonsoft.Json": "5.0.6"
        },
        "compile": {
          "lib/4.0/Hammock.ClientProfile.dll": {},
          "lib/4.0/Newtonsoft.Json.dll": {},
          "lib/4.0/TweetSharp.dll": {}
        },
        "runtime": {
          "lib/4.0/Hammock.ClientProfile.dll": {},
          "lib/4.0/Newtonsoft.Json.dll": {},
          "lib/4.0/TweetSharp.dll": {}
        }
      }
    },
    ".NETFramework,Version=v4.5/win7-x86": {
      "Hammock/1.3.1": {
        "type": "package",
        "compile": {
          "lib/4.0/Hammock.ClientProfile.dll": {},
          "lib/4.0/Hammock.dll": {}
        },
        "runtime": {
          "lib/4.0/Hammock.ClientProfile.dll": {},
          "lib/4.0/Hammock.dll": {}
        }
      },
      "IrcDotNet/0.5.0": {
        "type": "project",
        "framework": ".NETFramework,Version=v4.5"
      },
      "IrcDotNet.Samples.Common/0.5.0": {
        "type": "project",
        "framework": ".NETFramework,Version=v4.5",
        "dependencies": {
          "IrcDotNet": null
        }
      },
      "Newtonsoft.Json/5.0.6": {
        "type": "package",
        "compile": {
          "lib/net45/Newtonsoft.Json.dll": {}
        },
        "runtime": {
          "lib/net45/Newtonsoft.Json.dll": {}
        }
      },
      "TweetSharp/2.3.1": {
        "type": "package",
        "dependencies": {
          "Newtonsoft.Json": "5.0.6"
        },
        "compile": {
          "lib/4.0/Hammock.ClientProfile.dll": {},
          "lib/4.0/Newtonsoft.Json.dll": {},
          "lib/4.0/TweetSharp.dll": {}
        },
        "runtime": {
          "lib/4.0/Hammock.ClientProfile.dll": {},
          "lib/4.0/Newtonsoft.Json.dll": {},
          "lib/4.0/TweetSharp.dll": {}
        }
      }
    },
    ".NETFramework,Version=v4.5/win7-x64": {
      "Hammock/1.3.1": {
        "type": "package",
        "compile": {
          "lib/4.0/Hammock.ClientProfile.dll": {},
          "lib/4.0/Hammock.dll": {}
        },
        "runtime": {
          "lib/4.0/Hammock.ClientProfile.dll": {},
          "lib/4.0/Hammock.dll": {}
        }
      },
      "IrcDotNet/0.5.0": {
        "type": "project",
        "framework": ".NETFramework,Version=v4.5"
      },
      "IrcDotNet.Samples.Common/0.5.0": {
        "type": "project",
        "framework": ".NETFramework,Version=v4.5",
        "dependencies": {
          "IrcDotNet": null
        }
      },
      "Newtonsoft.Json/5.0.6": {
        "type": "package",
        "compile": {
          "lib/net45/Newtonsoft.Json.dll": {}
        },
        "runtime": {
          "lib/net45/Newtonsoft.Json.dll": {}
        }
      },
      "TweetSharp/2.3.1": {
        "type": "package",
        "dependencies": {
          "Newtonsoft.Json": "5.0.6"
        },
        "compile": {
          "lib/4.0/Hammock.ClientProfile.dll": {},
          "lib/4.0/Newtonsoft.Json.dll": {},
          "lib/4.0/TweetSharp.dll": {}
        },
        "runtime": {
          "lib/4.0/Hammock.ClientProfile.dll": {},
          "lib/4.0/Newtonsoft.Json.dll": {},
          "lib/4.0/TweetSharp.dll": {}
        }
      }
    },
    ".NETFramework,Version=v4.5.1/win7-x86": {
      "Hammock/1.3.1": {
        "type": "package",
        "compile": {
          "lib/4.0/Hammock.ClientProfile.dll": {},
          "lib/4.0/Hammock.dll": {}
        },
        "runtime": {
          "lib/4.0/Hammock.ClientProfile.dll": {},
          "lib/4.0/Hammock.dll": {}
        }
      },
      "IrcDotNet/0.5.0": {
        "type": "project",
        "framework": ".NETFramework,Version=v4.5.1"
      },
      "IrcDotNet.Samples.Common/0.5.0": {
        "type": "project",
        "framework": ".NETFramework,Version=v4.5.1",
        "dependencies": {
          "IrcDotNet": null
        }
      },
      "Newtonsoft.Json/5.0.6": {
        "type": "package",
        "compile": {
          "lib/net45/Newtonsoft.Json.dll": {}
        },
        "runtime": {
          "lib/net45/Newtonsoft.Json.dll": {}
        }
      },
      "TweetSharp/2.3.1": {
        "type": "package",
        "dependencies": {
          "Newtonsoft.Json": "5.0.6"
        },
        "compile": {
          "lib/4.0/Hammock.ClientProfile.dll": {},
          "lib/4.0/Newtonsoft.Json.dll": {},
          "lib/4.0/TweetSharp.dll": {}
        },
        "runtime": {
          "lib/4.0/Hammock.ClientProfile.dll": {},
          "lib/4.0/Newtonsoft.Json.dll": {},
          "lib/4.0/TweetSharp.dll": {}
        }
      }
    },
    ".NETFramework,Version=v4.5.1/win7-x64": {
      "Hammock/1.3.1": {
        "type": "package",
        "compile": {
          "lib/4.0/Hammock.ClientProfile.dll": {},
          "lib/4.0/Hammock.dll": {}
        },
        "runtime": {
          "lib/4.0/Hammock.ClientProfile.dll": {},
          "lib/4.0/Hammock.dll": {}
        }
      },
      "IrcDotNet/0.5.0": {
        "type": "project",
        "framework": ".NETFramework,Version=v4.5.1"
      },
      "IrcDotNet.Samples.Common/0.5.0": {
        "type": "project",
        "framework": ".NETFramework,Version=v4.5.1",
        "dependencies": {
          "IrcDotNet": null
        }
      },
      "Newtonsoft.Json/5.0.6": {
        "type": "package",
        "compile": {
          "lib/net45/Newtonsoft.Json.dll": {}
        },
        "runtime": {
          "lib/net45/Newtonsoft.Json.dll": {}
        }
      },
      "TweetSharp/2.3.1": {
        "type": "package",
        "dependencies": {
          "Newtonsoft.Json": "5.0.6"
        },
        "compile": {
          "lib/4.0/Hammock.ClientProfile.dll": {},
          "lib/4.0/Newtonsoft.Json.dll": {},
          "lib/4.0/TweetSharp.dll": {}
        },
        "runtime": {
          "lib/4.0/Hammock.ClientProfile.dll": {},
          "lib/4.0/Newtonsoft.Json.dll": {},
          "lib/4.0/TweetSharp.dll": {}
        }
      }
    },
    "DNX,Version=v4.5.1/win7-x86": {
      "Hammock/1.3.1": {
        "type": "package",
        "compile": {
          "lib/4.0/Hammock.ClientProfile.dll": {},
          "lib/4.0/Hammock.dll": {}
        },
        "runtime": {
          "lib/4.0/Hammock.ClientProfile.dll": {},
          "lib/4.0/Hammock.dll": {}
        }
      },
      "IrcDotNet/0.5.0": {
        "type": "project",
        "framework": "DNX,Version=v4.5.1"
      },
      "IrcDotNet.Samples.Common/0.5.0": {
        "type": "project",
        "framework": "DNX,Version=v4.5.1",
        "dependencies": {
          "IrcDotNet": null
        }
      },
      "Newtonsoft.Json/5.0.6": {
        "type": "package",
        "compile": {
          "lib/net45/Newtonsoft.Json.dll": {}
        },
        "runtime": {
          "lib/net45/Newtonsoft.Json.dll": {}
        }
      },
      "TweetSharp/2.3.1": {
        "type": "package",
        "dependencies": {
          "Newtonsoft.Json": "5.0.6"
        },
        "compile": {
          "lib/4.0/Hammock.ClientProfile.dll": {},
          "lib/4.0/Newtonsoft.Json.dll": {},
          "lib/4.0/TweetSharp.dll": {}
        },
        "runtime": {
          "lib/4.0/Hammock.ClientProfile.dll": {},
          "lib/4.0/Newtonsoft.Json.dll": {},
          "lib/4.0/TweetSharp.dll": {}
        }
      }
    },
    "DNX,Version=v4.5.1/win7-x64": {
      "Hammock/1.3.1": {
        "type": "package",
        "compile": {
          "lib/4.0/Hammock.ClientProfile.dll": {},
          "lib/4.0/Hammock.dll": {}
        },
        "runtime": {
          "lib/4.0/Hammock.ClientProfile.dll": {},
          "lib/4.0/Hammock.dll": {}
        }
      },
      "IrcDotNet/0.5.0": {
        "type": "project",
        "framework": "DNX,Version=v4.5.1"
      },
      "IrcDotNet.Samples.Common/0.5.0": {
        "type": "project",
        "framework": "DNX,Version=v4.5.1",
        "dependencies": {
          "IrcDotNet": null
        }
      },
      "Newtonsoft.Json/5.0.6": {
        "type": "package",
        "compile": {
          "lib/net45/Newtonsoft.Json.dll": {}
        },
        "runtime": {
          "lib/net45/Newtonsoft.Json.dll": {}
        }
      },
      "TweetSharp/2.3.1": {
        "type": "package",
        "dependencies": {
          "Newtonsoft.Json": "5.0.6"
        },
        "compile": {
          "lib/4.0/Hammock.ClientProfile.dll": {},
          "lib/4.0/Newtonsoft.Json.dll": {},
          "lib/4.0/TweetSharp.dll": {}
        },
        "runtime": {
          "lib/4.0/Hammock.ClientProfile.dll": {},
          "lib/4.0/Newtonsoft.Json.dll": {},
          "lib/4.0/TweetSharp.dll": {}
        }
      }
    },
    "DNX,Version=v5.0/win7-x86": {
      "Hammock/1.3.1": {
        "type": "package",
        "compile": {
          "lib/4.0/Hammock.ClientProfile.dll": {},
          "lib/4.0/Hammock.dll": {}
        },
        "runtime": {
          "lib/4.0/Hammock.ClientProfile.dll": {},
          "lib/4.0/Hammock.dll": {}
        }
      },
      "IrcDotNet/0.5.0": {
        "type": "project",
        "framework": "DNX,Version=v4.5.1"
      },
      "IrcDotNet.Samples.Common/0.5.0": {
        "type": "project",
        "framework": "DNX,Version=v5.0",
        "dependencies": {
          "IrcDotNet": null
        }
      },
      "Newtonsoft.Json/5.0.6": {
        "type": "package",
        "compile": {
          "lib/net45/Newtonsoft.Json.dll": {}
        },
        "runtime": {
          "lib/net45/Newtonsoft.Json.dll": {}
        }
      },
      "TweetSharp/2.3.1": {
        "type": "package",
        "dependencies": {
          "Newtonsoft.Json": "5.0.6"
        },
        "compile": {
          "lib/4.0/Hammock.ClientProfile.dll": {},
          "lib/4.0/Newtonsoft.Json.dll": {},
          "lib/4.0/TweetSharp.dll": {}
        },
        "runtime": {
          "lib/4.0/Hammock.ClientProfile.dll": {},
          "lib/4.0/Newtonsoft.Json.dll": {},
          "lib/4.0/TweetSharp.dll": {}
        }
      }
    },
    "DNX,Version=v5.0/win7-x64": {
      "Hammock/1.3.1": {
        "type": "package",
        "compile": {
          "lib/4.0/Hammock.ClientProfile.dll": {},
          "lib/4.0/Hammock.dll": {}
        },
        "runtime": {
          "lib/4.0/Hammock.ClientProfile.dll": {},
          "lib/4.0/Hammock.dll": {}
        }
      },
      "IrcDotNet/0.5.0": {
        "type": "project",
        "framework": "DNX,Version=v4.5.1"
      },
      "IrcDotNet.Samples.Common/0.5.0": {
        "type": "project",
        "framework": "DNX,Version=v5.0",
        "dependencies": {
          "IrcDotNet": null
        }
      },
      "Newtonsoft.Json/5.0.6": {
        "type": "package",
        "compile": {
          "lib/net45/Newtonsoft.Json.dll": {}
        },
        "runtime": {
          "lib/net45/Newtonsoft.Json.dll": {}
        }
      },
      "TweetSharp/2.3.1": {
        "type": "package",
        "dependencies": {
          "Newtonsoft.Json": "5.0.6"
        },
        "compile": {
          "lib/4.0/Hammock.ClientProfile.dll": {},
          "lib/4.0/Newtonsoft.Json.dll": {},
          "lib/4.0/TweetSharp.dll": {}
        },
        "runtime": {
          "lib/4.0/Hammock.ClientProfile.dll": {},
          "lib/4.0/Newtonsoft.Json.dll": {},
          "lib/4.0/TweetSharp.dll": {}
        }
      }
    }
  },
  "libraries": {
    "IrcDotNet/0.5.0": {
      "type": "project",
      "path": "../../source/IrcDotNet/project.json"
    },
    "IrcDotNet.Samples.Common/0.5.0": {
      "type": "project",
      "path": "../IrcDotNet.Samples.Common/project.json"
    },
    "Hammock/1.3.1": {
      "type": "package",
      "sha512": "hoELpXuahVbJtZwGP06yby0yN2gBQfj9d/VMDanTa7xNVzeEAgKS9zsH3ebRmaSVaxN6YuIeM20pQRDiyh5ojw==",
      "files": [
        "Hammock.1.3.1.nupkg",
        "Hammock.1.3.1.nupkg.sha512",
        "Hammock.nuspec",
        "lib/2.0/Hammock.dll",
        "lib/2.0/Hammock.pdb",
        "lib/2.0/LinqBridge.dll",
        "lib/3.5/Hammock.ClientProfile.dll",
        "lib/3.5/Hammock.ClientProfile.pdb",
        "lib/3.5/Hammock.dll",
        "lib/3.5/Hammock.pdb",
        "lib/4.0/Hammock.ClientProfile.dll",
        "lib/4.0/Hammock.ClientProfile.pdb",
        "lib/4.0/Hammock.dll",
        "lib/4.0/Hammock.pdb",
        "lib/sl4/de/Microsoft.CSharp.resources.dll",
        "lib/sl4/de/System.Json.resources.dll",
        "lib/sl4/de/System.Runtime.Serialization.Json.resources.dll",
        "lib/sl4/de/System.Xml.Linq.resources.dll",
        "lib/sl4/es/Microsoft.CSharp.resources.dll",
        "lib/sl4/es/System.Json.resources.dll",
        "lib/sl4/es/System.Runtime.Serialization.Json.resources.dll",
        "lib/sl4/es/System.Xml.Linq.resources.dll",
        "lib/sl4/fr/Microsoft.CSharp.resources.dll",
        "lib/sl4/fr/System.Json.resources.dll",
        "lib/sl4/fr/System.Runtime.Serialization.Json.resources.dll",
        "lib/sl4/fr/System.Xml.Linq.resources.dll",
        "lib/sl4/Hammock.Silverlight.dll",
        "lib/sl4/Hammock.Silverlight.pdb",
        "lib/sl4/ICSharpCode.SharpZipLib.Silverlight.dll",
        "lib/sl4/ICSharpCode.SharpZipLib.Silverlight.pdb",
        "lib/sl4/it/Microsoft.CSharp.resources.dll",
        "lib/sl4/it/System.Json.resources.dll",
        "lib/sl4/it/System.Runtime.Serialization.Json.resources.dll",
        "lib/sl4/it/System.Xml.Linq.resources.dll",
        "lib/sl4/ja/Microsoft.CSharp.resources.dll",
        "lib/sl4/ja/System.Json.resources.dll",
        "lib/sl4/ja/System.Runtime.Serialization.Json.resources.dll",
        "lib/sl4/ja/System.Xml.Linq.resources.dll",
        "lib/sl4/ko/Microsoft.CSharp.resources.dll",
        "lib/sl4/ko/System.Json.resources.dll",
        "lib/sl4/ko/System.Runtime.Serialization.Json.resources.dll",
        "lib/sl4/ko/System.Xml.Linq.resources.dll",
        "lib/sl4/Microsoft.CSharp.dll",
        "lib/sl4/Microsoft.CSharp.xml",
        "lib/sl4/ru/Microsoft.CSharp.resources.dll",
        "lib/sl4/ru/System.Json.resources.dll",
        "lib/sl4/ru/System.Runtime.Serialization.Json.resources.dll",
        "lib/sl4/ru/System.Xml.Linq.resources.dll",
        "lib/sl4/System.Json.dll",
        "lib/sl4/System.Json.xml",
        "lib/sl4/System.Runtime.Serialization.Json.dll",
        "lib/sl4/System.Runtime.Serialization.Json.xml",
        "lib/sl4/System.Xml.Linq.dll",
        "lib/sl4/System.Xml.Linq.xml",
        "lib/sl4/zh-Hans/Microsoft.CSharp.resources.dll",
        "lib/sl4/zh-Hans/System.Json.resources.dll",
        "lib/sl4/zh-Hans/System.Runtime.Serialization.Json.resources.dll",
        "lib/sl4/zh-Hans/System.Xml.Linq.resources.dll",
        "lib/sl4/zh-Hant/Microsoft.CSharp.resources.dll",
        "lib/sl4/zh-Hant/System.Json.resources.dll",
        "lib/sl4/zh-Hant/System.Runtime.Serialization.Json.resources.dll",
        "lib/sl4/zh-Hant/System.Xml.Linq.resources.dll",
        "lib/sl4-wp/Hammock.WindowsPhone.dll",
        "lib/sl4-wp/Hammock.WindowsPhone.pdb",
        "lib/sl4-wp/ICSharpCode.SharpZipLib.WindowsPhone.dll",
        "lib/sl4-wp/ICSharpCode.SharpZipLib.WindowsPhone.pdb",
        "lib/sl4-wp71/Hammock.WindowsPhone.Mango.dll",
        "lib/sl4-wp71/Hammock.WindowsPhone.Mango.pdb",
        "lib/sl4-wp71/ICSharpCode.SharpZipLib.WindowsPhone.dll",
        "lib/sl4-wp71/ICSharpCode.SharpZipLib.WindowsPhone.pdb",
        "LICENSE.md",
        "README.md"
      ]
    },
    "Newtonsoft.Json/5.0.6": {
      "type": "package",
      "sha512": "Z594WlU7Wndv4vQxwsS7ym2y2Izsuw5U86UxQbx6YIKIjVju7V7OU4l1QQl5fM9AmPdzWIOxSlonzuQzzulMaw==",
      "files": [
        "lib/net20/Newtonsoft.Json.dll",
        "lib/net20/Newtonsoft.Json.xml",
        "lib/net35/Newtonsoft.Json.dll",
        "lib/net35/Newtonsoft.Json.xml",
        "lib/net40/Newtonsoft.Json.dll",
        "lib/net40/Newtonsoft.Json.xml",
        "lib/net45/Newtonsoft.Json.dll",
        "lib/net45/Newtonsoft.Json.xml",
        "lib/netcore45/Newtonsoft.Json.dll",
        "lib/netcore45/Newtonsoft.Json.xml",
        "lib/portable-net40+sl4+wp7+win8/Newtonsoft.Json.dll",
        "lib/portable-net40+sl4+wp7+win8/Newtonsoft.Json.xml",
        "lib/portable-net45+wp80+win8/Newtonsoft.Json.dll",
        "lib/portable-net45+wp80+win8/Newtonsoft.Json.xml",
        "Newtonsoft.Json.5.0.6.nupkg",
        "Newtonsoft.Json.5.0.6.nupkg.sha512",
        "Newtonsoft.Json.nuspec"
      ]
    },
    "TweetSharp/2.3.1": {
      "type": "package",
      "sha512": "0iN3kZ+idHMZ2L9F1Hxnt4kCO4s53hfLu+erANQhP3chwsRrEgGjCpjo9OOM27sHCKNHd9e9iSrymQ9EtXlUOQ==",
      "files": [
        "lib/2.0/Hammock.dll",
        "lib/2.0/Hammock.pdb",
        "lib/2.0/Newtonsoft.Json.dll",
        "lib/2.0/Newtonsoft.Json.xml",
        "lib/2.0/TweetSharp.dll",
        "lib/2.0/TweetSharp.pdb",
        "lib/3.5/Hammock.ClientProfile.dll",
        "lib/3.5/Hammock.ClientProfile.pdb",
        "lib/3.5/Newtonsoft.Json.dll",
        "lib/3.5/Newtonsoft.Json.xml",
        "lib/3.5/TweetSharp.dll",
        "lib/3.5/TweetSharp.pdb",
        "lib/4.0/Hammock.ClientProfile.dll",
        "lib/4.0/Hammock.ClientProfile.pdb",
        "lib/4.0/Newtonsoft.Json.dll",
        "lib/4.0/Newtonsoft.Json.xml",
        "lib/4.0/TweetSharp.dll",
        "lib/4.0/TweetSharp.pdb",
        "lib/sl4/de/System.Xml.Linq.resources.dll",
        "lib/sl4/es/System.Xml.Linq.resources.dll",
        "lib/sl4/fr/System.Xml.Linq.resources.dll",
        "lib/sl4/Hammock.Silverlight.dll",
        "lib/sl4/Hammock.Silverlight.pdb",
        "lib/sl4/ICSharpCode.SharpZipLib.Silverlight.dll",
        "lib/sl4/ICSharpCode.SharpZipLib.Silverlight.pdb",
        "lib/sl4/it/System.Xml.Linq.resources.dll",
        "lib/sl4/ja/System.Xml.Linq.resources.dll",
        "lib/sl4/ko/System.Xml.Linq.resources.dll",
        "lib/sl4/Newtonsoft.Json.dll",
        "lib/sl4/Newtonsoft.Json.xml",
        "lib/sl4/ru/System.Xml.Linq.resources.dll",
        "lib/sl4/System.Xml.Linq.dll",
        "lib/sl4/System.Xml.Linq.xml",
        "lib/sl4/TweetSharp.Silverlight.dll",
        "lib/sl4/TweetSharp.Silverlight.pdb",
        "lib/sl4/zh-Hans/System.Xml.Linq.resources.dll",
        "lib/sl4/zh-Hant/System.Xml.Linq.resources.dll",
        "lib/sl4-wp/Hammock.WindowsPhone.dll",
        "lib/sl4-wp/Hammock.WindowsPhone.pdb",
        "lib/sl4-wp/ICSharpCode.SharpZipLib.WindowsPhone.dll",
        "lib/sl4-wp/ICSharpCode.SharpZipLib.WindowsPhone.pdb",
        "lib/sl4-wp/Newtonsoft.Json.dll",
        "lib/sl4-wp/Newtonsoft.Json.xml",
        "lib/sl4-wp/TweetSharp.WindowsPhone.dll",
        "lib/sl4-wp/TweetSharp.WindowsPhone.pdb",
        "lib/sl4-wp71/Hammock.WindowsPhone.Mango.dll",
        "lib/sl4-wp71/Hammock.WindowsPhone.Mango.pdb",
        "lib/sl4-wp71/ICSharpCode.SharpZipLib.WindowsPhone.dll",
        "lib/sl4-wp71/ICSharpCode.SharpZipLib.WindowsPhone.pdb",
        "lib/sl4-wp71/Newtonsoft.Json.dll",
        "lib/sl4-wp71/Newtonsoft.Json.xml",
        "lib/sl4-wp71/TweetSharp.WindowsPhone.Mango.dll",
        "lib/sl4-wp71/TweetSharp.WindowsPhone.Mango.pdb",
        "LICENSE.md",
        "README.md",
        "TweetSharp.2.3.1.nupkg",
        "TweetSharp.2.3.1.nupkg.sha512",
        "TweetSharp.nuspec"
      ]
    }
  },
  "projectFileDependencyGroups": {
    "": [
      "IrcDotNet.Samples.Common ",
      "Hammock >= 1.3.1",
      "Newtonsoft.Json >= 5.0.6",
      "TweetSharp >= 2.3.1"
    ],
    ".NETFramework,Version=v4.0": [],
    ".NETFramework,Version=v4.5": [],
    ".NETFramework,Version=v4.5.1": [],
    "DNX,Version=v4.5.1": [],
    "DNX,Version=v5.0": []
  }
}